{
    "STL10": [
        {
            "acc/test/STL10_epoch": 0.9828749895095825,
            "loss/test/STL10_epoch": 0.061543770134449005,
            "acc/test/STL10": 0.9828749895095825,
            "normalized_acc/test/STL10": 0.9949386119842529
        }
    ],
    "CIFAR100": [
        {
            "acc/test/CIFAR100_epoch": 0.8848000168800354,
            "loss/test/CIFAR100_epoch": 0.4673994481563568,
            "acc/test/CIFAR100": 0.8848000168800354,
            "normalized_acc/test/CIFAR100": 0.991150438785553
        }
    ],
    "avg": [
        {
            "acc/test/avg": 0.933837503194809,
            "normalized_acc/test/avg": 0.993044525384903
        }
    ]
}