{
    "GTSRB": [
        {
            "acc/test/GTSRB_epoch": 0.9747426509857178,
            "loss/test/GTSRB_epoch": 0.11017685383558273,
            "acc/test/GTSRB": 0.9747426509857178,
            "normalized_acc/test/GTSRB": 0.9854318499565125
        }
    ],
    "DTD": [
        {
            "acc/test/DTD_epoch": 0.7202127575874329,
            "loss/test/DTD_epoch": 1.0690555572509766,
            "acc/test/DTD": 0.7202127575874329,
            "normalized_acc/test/DTD": 0.8690628409385681
        }
    ],
    "avg": [
        {
            "acc/test/avg": 0.8474777042865753,
            "normalized_acc/test/avg": 0.9272473454475403
        }
    ]
}