{
    "RESISC45": [
        {
            "acc/test/RESISC45": 0.8788889050483704,
            "loss/test/RESISC45": 0.38312333822250366,
            "normalized_acc/test/RESISC45": 0.9091954231262207
        }
    ],
    "Food101": [
        {
            "acc/test/Food101": 0.9140594005584717,
            "loss/test/Food101": 0.30396121740341187,
            "normalized_acc/test/Food101": 1.0055768489837646
        }
    ],
    "avg": [
        {
            "acc/test/avg": 0.896474152803421,
            "normalized_acc/test/avg": 0.9573861360549927
        }
    ]
}