{
  "Cars": [
    {
      "acc/test/Cars_epoch": 0.5466981530189514,
      "loss/test/Cars_epoch": 1.6934270858764648,
      "acc/test/Cars": 0.5466981530189514,
      "normalized_acc/test/Cars": 0.6371937990188599
    }
  ],
  "PCAM": [
    {
      "acc/test/PCAM_epoch": 0.78240966796875,
      "loss/test/PCAM_epoch": 0.4452800154685974,
      "acc/test/PCAM": 0.78240966796875,
      "normalized_acc/test/PCAM": 0.8818491101264954
    }
  ],
  "STL10": [
    {
      "acc/test/STL10_epoch": 0.9698749780654907,
      "loss/test/STL10_epoch": 0.09767598658800125,
      "acc/test/STL10": 0.9698749780654907,
      "normalized_acc/test/STL10": 0.9817790389060974
    }
  ],
  "CIFAR10": [
    {
      "acc/test/CIFAR10_epoch": 0.9605000019073486,
      "loss/test/CIFAR10_epoch": 0.13114142417907715,
      "acc/test/CIFAR10": 0.9605000019073486,
      "normalized_acc/test/CIFAR10": 0.978504478931427
    }
  ],
  "EMNIST": [
    {
      "acc/test/EMNIST_epoch": 0.9829000234603882,
      "loss/test/EMNIST_epoch": 0.26359209418296814,
      "acc/test/EMNIST": 0.9829000234603882,
      "normalized_acc/test/EMNIST": 0.988534688949585
    }
  ],
  "avg": [
    {
      "acc/test/avg": 0.8484765648841858,
      "normalized_acc/test/avg": 0.8935722231864929
    }
  ]
}