{
    "Cars": [
        {
            "acc/test/Cars_epoch": 0.8054968118667603,
            "loss/test/Cars_epoch": 0.5854244232177734,
            "acc/test/Cars": 0.8054968118667603,
            "normalized_acc/test/Cars": 0.9388316869735718
        }
    ],
    "KMNIST": [
        {
            "acc/test/KMNIST_epoch": 0.23430000245571136,
            "loss/test/KMNIST_epoch": 2.095104932785034,
            "acc/test/KMNIST": 0.23430000245571136,
            "normalized_acc/test/KMNIST": 0.23823080956935883
        }
    ],
    "avg": [
        {
            "acc/test/avg": 0.5198984071612358,
            "normalized_acc/test/avg": 0.5885312482714653
        }
    ]
}