{
    "SUN397": [
        {
            "acc/test/SUN397_epoch": 0.740856409072876,
            "loss/test/SUN397_epoch": 0.8889248371124268,
            "acc/test/SUN397": 0.740856409072876,
            "normalized_acc/test/SUN397": 0.9395604133605957
        }
    ],
    "CIFAR10": [
        {
            "acc/test/CIFAR10_epoch": 0.9757999777793884,
            "loss/test/CIFAR10_epoch": 0.078925222158432,
            "acc/test/CIFAR10": 0.9757999777793884,
            "normalized_acc/test/CIFAR10": 0.994091272354126
        }
    ],
    "avg": [
        {
            "acc/test/avg": 0.8583281934261322,
            "normalized_acc/test/avg": 0.9668258428573608
        }
    ]
}