{
    "MNIST": [
        {
            "acc/test/MNIST_epoch": 0.9947999715805054,
            "loss/test/MNIST_epoch": 0.044115208089351654,
            "acc/test/MNIST": 0.9947999715805054,
            "normalized_acc/test/MNIST": 0.9982939958572388
        }
    ],
    "PCAM": [
        {
            "acc/test/PCAM_epoch": 0.872039794921875,
            "loss/test/PCAM_epoch": 0.3632515072822571,
            "acc/test/PCAM": 0.872039794921875,
            "normalized_acc/test/PCAM": 0.9828706979751587
        }
    ],
    "avg": [
        {
            "acc/test/avg": 0.9334198832511902,
            "normalized_acc/test/avg": 0.9905823469161987
        }
    ]
}