{
    "STL10": [
        {
            "acc/test/STL10_epoch": 0.9860000014305115,
            "loss/test/STL10_epoch": 0.04426640272140503,
            "acc/test/STL10": 0.9860000014305115,
            "normalized_acc/test/STL10": 0.9981020092964172
        }
    ],
    "CIFAR100": [
        {
            "acc/test/CIFAR100_epoch": 0.8827000260353088,
            "loss/test/CIFAR100_epoch": 0.4711191952228546,
            "acc/test/CIFAR100": 0.8827000260353088,
            "normalized_acc/test/CIFAR100": 0.9887980222702026
        }
    ],
    "avg": [
        {
            "acc/test/avg": 0.9343500137329102,
            "normalized_acc/test/avg": 0.9934500157833099
        }
    ]
}