{
    "CIFAR10": [
        {
            "acc/test/CIFAR10_epoch": 0.9660999774932861,
            "loss/test/CIFAR10_epoch": 0.11440204828977585,
            "acc/test/CIFAR10": 0.9660999774932861,
            "normalized_acc/test/CIFAR10": 0.984209418296814
        }
    ],
    "EMNIST": [
        {
            "acc/test/EMNIST_epoch": 0.9258000254631042,
            "loss/test/EMNIST_epoch": 0.5874531865119934,
            "acc/test/EMNIST": 0.9258000254631042,
            "normalized_acc/test/EMNIST": 0.9311073422431946
        }
    ],
    "avg": [
        {
            "acc/test/avg": 0.9459500014781952,
            "normalized_acc/test/avg": 0.9576583802700043
        }
    ]
}