{
    "MNIST": [
        {
            "acc/test/MNIST_epoch": 0.9398000240325928,
            "loss/test/MNIST_epoch": 0.664250373840332,
            "acc/test/MNIST": 0.9398000240325928,
            "normalized_acc/test/MNIST": 0.9431008696556091
        }
    ],
    "FER2013": [
        {
            "acc/test/FER2013_epoch": 0.6025355458259583,
            "loss/test/FER2013_epoch": 1.1153892278671265,
            "acc/test/FER2013": 0.6025355458259583,
            "normalized_acc/test/FER2013": 0.8172714114189148
        }
    ],
    "avg": [
        {
            "acc/test/avg": 0.7711677849292755,
            "normalized_acc/test/avg": 0.880186140537262
        }
    ]
}