{
    "Cars": [
        {
            "acc/test/Cars_epoch": 0.8224101662635803,
            "loss/test/Cars_epoch": 0.5597842931747437,
            "acc/test/Cars": 0.8224101662635803,
            "normalized_acc/test/Cars": 0.9585447311401367
        }
    ],
    "STL10": [
        {
            "acc/test/STL10_epoch": 0.987500011920929,
            "loss/test/STL10_epoch": 0.038767263293266296,
            "acc/test/STL10": 0.987500011920929,
            "normalized_acc/test/STL10": 0.9996204376220703
        }
    ],
    "avg": [
        {
            "acc/test/avg": 0.9049550890922546,
            "normalized_acc/test/avg": 0.9790825843811035
        }
    ]
}