{
    "GTSRB": [
        {
            "acc/test/GTSRB": 0.9781472682952881,
            "loss/test/GTSRB": 0.10355857759714127,
            "normalized_acc/test/GTSRB": 0.9888737797737122
        }
    ],
    "Flowers102": [
        {
            "acc/test/Flowers102": 0.8276142477989197,
            "loss/test/Flowers102": 0.7240990400314331,
            "normalized_acc/test/Flowers102": 0.8783223628997803
        }
    ],
    "avg": [
        {
            "acc/test/avg": 0.9028807580471039,
            "normalized_acc/test/avg": 0.9335980713367462
        }
    ]
}