{
    "DTD": [
        {
            "acc/test/DTD_epoch": 0.6308510899543762,
            "loss/test/DTD_epoch": 1.3025236129760742,
            "acc/test/DTD": 0.6308510899543762,
            "normalized_acc/test/DTD": 0.7612323760986328
        }
    ],
    "FER2013": [
        {
            "acc/test/FER2013_epoch": 0.5929228067398071,
            "loss/test/FER2013_epoch": 1.1244218349456787,
            "acc/test/FER2013": 0.5929228067398071,
            "normalized_acc/test/FER2013": 0.8042327761650085
        }
    ],
    "avg": [
        {
            "acc/test/avg": 0.6118869483470917,
            "normalized_acc/test/avg": 0.7827325761318207
        }
    ]
}