{
    "EuroSAT": [
        {
            "acc/test/EuroSAT_epoch": 0.9081481695175171,
            "loss/test/EuroSAT_epoch": 0.4515911638736725,
            "acc/test/EuroSAT": 0.9081481695175171,
            "normalized_acc/test/EuroSAT": 0.9166355729103088
        }
    ],
    "PCAM": [
        {
            "acc/test/PCAM_epoch": 0.7835693359375,
            "loss/test/PCAM_epoch": 0.4851025938987732,
            "acc/test/PCAM": 0.7835693359375,
            "normalized_acc/test/PCAM": 0.8831561803817749
        }
    ],
    "avg": [
        {
            "acc/test/avg": 0.8458587527275085,
            "normalized_acc/test/avg": 0.8998958766460419
        }
    ]
}