{
    "SUN397": [
        {
            "acc/test/SUN397_epoch": 0.7777329683303833,
            "loss/test/SUN397_epoch": 0.8646758198738098,
            "acc/test/SUN397": 0.7777329683303833,
            "normalized_acc/test/SUN397": 0.986327588558197
        }
    ],
    "FER2013": [
        {
            "acc/test/FER2013_epoch": 0.7359988689422607,
            "loss/test/FER2013_epoch": 1.1690973043441772,
            "acc/test/FER2013": 0.7359988689422607,
            "normalized_acc/test/FER2013": 0.9982993006706238
        }
    ],
    "avg": [
        {
            "acc/test/avg": 0.756865918636322,
            "normalized_acc/test/avg": 0.9923134446144104
        }
    ]
}