{
    "Cars": [
        {
            "acc/test/Cars_epoch": 0.7336152195930481,
            "loss/test/Cars_epoch": 0.7621796727180481,
            "acc/test/Cars": 0.7336152195930481,
            "normalized_acc/test/Cars": 0.8550514578819275
        }
    ],
    "RESISC45": [
        {
            "acc/test/RESISC45_epoch": 0.7993651032447815,
            "loss/test/RESISC45_epoch": 0.6312061548233032,
            "acc/test/RESISC45": 0.7993651032447815,
            "normalized_acc/test/RESISC45": 0.8269294500350952
        }
    ],
    "avg": [
        {
            "acc/test/avg": 0.7664901614189148,
            "normalized_acc/test/avg": 0.8409904539585114
        }
    ]
}