{
    "MNIST": [
        {
            "acc/test/MNIST_epoch": 0.9958000183105469,
            "loss/test/MNIST_epoch": 0.03009454905986786,
            "acc/test/MNIST": 0.9958000183105469,
            "normalized_acc/test/MNIST": 0.999297559261322
        }
    ],
    "Food101": [
        {
            "acc/test/Food101_epoch": 0.8761584162712097,
            "loss/test/Food101_epoch": 0.5238143801689148,
            "acc/test/Food101": 0.8761584162712097,
            "normalized_acc/test/Food101": 0.9638811349868774
        }
    ],
    "avg": [
        {
            "acc/test/avg": 0.9359792172908783,
            "normalized_acc/test/avg": 0.9815893471240997
        }
    ]
}