{
    "PCAM": [
        {
            "acc/test/PCAM_epoch": 0.856719970703125,
            "loss/test/PCAM_epoch": 0.3447769284248352,
            "acc/test/PCAM": 0.856719970703125,
            "normalized_acc/test/PCAM": 0.9656038284301758
        }
    ],
    "CIFAR100": [
        {
            "acc/test/CIFAR100_epoch": 0.8051000237464905,
            "loss/test/CIFAR100_epoch": 0.6871079206466675,
            "acc/test/CIFAR100": 0.8051000237464905,
            "normalized_acc/test/CIFAR100": 0.9018707275390625
        }
    ],
    "avg": [
        {
            "acc/test/avg": 0.8309099972248077,
            "normalized_acc/test/avg": 0.9337372779846191
        }
    ]
}