{
    "MNIST": [
        {
            "acc/test/MNIST_epoch": 0.9934999942779541,
            "loss/test/MNIST_epoch": 0.05289497226476669,
            "acc/test/MNIST": 0.9934999942779541,
            "normalized_acc/test/MNIST": 0.9969894289970398
        }
    ],
    "FashionMNIST": [
        {
            "acc/test/FashionMNIST_epoch": 0.9003999829292297,
            "loss/test/FashionMNIST_epoch": 0.3229528069496155,
            "acc/test/FashionMNIST": 0.9003999829292297,
            "normalized_acc/test/FashionMNIST": 0.9457982778549194
        }
    ],
    "avg": [
        {
            "acc/test/avg": 0.9469499886035919,
            "normalized_acc/test/avg": 0.9713938534259796
        }
    ]
}