{
    "CIFAR100": [
        {
            "acc/test/CIFAR100_epoch": 0.8741999864578247,
            "loss/test/CIFAR100_epoch": 0.47798582911491394,
            "acc/test/CIFAR100": 0.8741999864578247,
            "normalized_acc/test/CIFAR100": 0.9792762994766235
        }
    ],
    "RenderedSST2": [
        {
            "acc/test/RenderedSST2_epoch": 0.7550796270370483,
            "loss/test/RenderedSST2_epoch": 0.5458641052246094,
            "acc/test/RenderedSST2": 0.7550796270370483,
            "normalized_acc/test/RenderedSST2": 0.9786476492881775
        }
    ],
    "avg": [
        {
            "acc/test/avg": 0.8146398067474365,
            "normalized_acc/test/avg": 0.9789619743824005
        }
    ]
}