{
    "STL10": [
        {
            "acc/test/STL10_epoch": 0.9863749742507935,
            "loss/test/STL10_epoch": 0.04171932116150856,
            "acc/test/STL10": 0.9863749742507935,
            "normalized_acc/test/STL10": 0.9984815716743469
        }
    ],
    "EMNIST": [
        {
            "acc/test/EMNIST_epoch": 0.9957000017166138,
            "loss/test/EMNIST_epoch": 0.04862461984157562,
            "acc/test/EMNIST": 0.9957000017166138,
            "normalized_acc/test/EMNIST": 1.0014079809188843
        }
    ],
    "avg": [
        {
            "acc/test/avg": 0.9910374879837036,
            "normalized_acc/test/avg": 0.9999447762966156
        }
    ]
}