{
    "DTD": [
        {
            "acc/test/DTD": 0.5648936033248901,
            "loss/test/DTD": 1.5209630727767944,
            "normalized_acc/test/DTD": 0.6816430687904358
        }
    ],
    "Flowers102": [
        {
            "acc/test/Flowers102": 0.8211091160774231,
            "loss/test/Flowers102": 0.723720133304596,
            "normalized_acc/test/Flowers102": 0.8714186549186707
        }
    ],
    "avg": [
        {
            "acc/test/avg": 0.6930013597011566,
            "normalized_acc/test/avg": 0.7765308618545532
        }
    ]
}