{
    "PCAM": [
        {
            "acc/test/PCAM_epoch": 0.7177734375,
            "loss/test/PCAM_epoch": 0.5138702392578125,
            "acc/test/PCAM": 0.7177734375,
            "normalized_acc/test/PCAM": 0.8089980483055115
        }
    ],
    "Food101": [
        {
            "acc/test/Food101_epoch": 0.9032078981399536,
            "loss/test/Food101_epoch": 0.33134812116622925,
            "acc/test/Food101": 0.9032078981399536,
            "normalized_acc/test/Food101": 0.9936388731002808
        }
    ],
    "avg": [
        {
            "acc/test/avg": 0.8104906678199768,
            "normalized_acc/test/avg": 0.9013184607028961
        }
    ]
}