{
    "MNIST": [
        {
            "acc/test/MNIST_epoch": 0.9929999709129333,
            "loss/test/MNIST_epoch": 0.03927026316523552,
            "acc/test/MNIST": 0.9929999709129333,
            "normalized_acc/test/MNIST": 0.9964876770973206
        }
    ],
    "KMNIST": [
        {
            "acc/test/KMNIST_epoch": 0.887499988079071,
            "loss/test/KMNIST_epoch": 0.4371754825115204,
            "acc/test/KMNIST": 0.887499988079071,
            "normalized_acc/test/KMNIST": 0.902389407157898
        }
    ],
    "avg": [
        {
            "acc/test/avg": 0.9402499794960022,
            "normalized_acc/test/avg": 0.9494385421276093
        }
    ]
}