{
    "GTSRB": [
        {
            "acc/test/GTSRB_epoch": 0.7164687514305115,
            "loss/test/GTSRB_epoch": 1.0913938283920288,
            "acc/test/GTSRB": 0.7164687514305115,
            "normalized_acc/test/GTSRB": 0.7243256568908691
        }
    ],
    "PCAM": [
        {
            "acc/test/PCAM_epoch": 0.87213134765625,
            "loss/test/PCAM_epoch": 0.3229953348636627,
            "acc/test/PCAM": 0.87213134765625,
            "normalized_acc/test/PCAM": 0.9829738736152649
        }
    ],
    "avg": [
        {
            "acc/test/avg": 0.7943000495433807,
            "normalized_acc/test/avg": 0.853649765253067
        }
    ]
}