{
    "RESISC45": [
        {
            "acc/test/RESISC45_epoch": 0.8192063570022583,
            "loss/test/RESISC45_epoch": 0.5619590282440186,
            "acc/test/RESISC45": 0.8192063570022583,
            "normalized_acc/test/RESISC45": 0.8474549055099487
        }
    ],
    "DTD": [
        {
            "acc/test/DTD_epoch": 0.5377659797668457,
            "loss/test/DTD_epoch": 1.639491319656372,
            "acc/test/DTD": 0.5377659797668457,
            "normalized_acc/test/DTD": 0.6489088535308838
        }
    ],
    "avg": [
        {
            "acc/test/avg": 0.678486168384552,
            "normalized_acc/test/avg": 0.7481818795204163
        }
    ]
}