{
    "Flowers102": [
        {
            "acc/test/Flowers102_epoch": 0.7986664772033691,
            "loss/test/Flowers102_epoch": 0.80575031042099,
            "acc/test/Flowers102": 0.7986664772033691,
            "normalized_acc/test/Flowers102": 0.8476009964942932
        }
    ],
    "RenderedSST2": [
        {
            "acc/test/RenderedSST2_epoch": 0.7402526140213013,
            "loss/test/RenderedSST2_epoch": 0.5249233841896057,
            "acc/test/RenderedSST2": 0.7402526140213013,
            "normalized_acc/test/RenderedSST2": 0.9594305753707886
        }
    ],
    "avg": [
        {
            "acc/test/avg": 0.7694595456123352,
            "normalized_acc/test/avg": 0.9035157859325409
        }
    ]
}