{
    "SUN397": [
        {
            "acc/test/SUN397_epoch": 0.7493199110031128,
            "loss/test/SUN397_epoch": 0.919349730014801,
            "acc/test/SUN397": 0.7493199110031128,
            "normalized_acc/test/SUN397": 0.9502938985824585
        }
    ],
    "DTD": [
        {
            "acc/test/DTD_epoch": 0.625,
            "loss/test/DTD_epoch": 1.4073487520217896,
            "acc/test/DTD": 0.625,
            "normalized_acc/test/DTD": 0.7541719675064087
        }
    ],
    "avg": [
        {
            "acc/test/avg": 0.6871599555015564,
            "normalized_acc/test/avg": 0.8522329330444336
        }
    ]
}