{
    "SVHN": [
        {
            "acc/test/SVHN_epoch": 0.9282421469688416,
            "loss/test/SVHN_epoch": 0.32880839705467224,
            "acc/test/SVHN": 0.9282421469688416,
            "normalized_acc/test/SVHN": 0.9521632790565491
        }
    ],
    "DTD": [
        {
            "acc/test/DTD_epoch": 0.6228723526000977,
            "loss/test/DTD_epoch": 1.344933271408081,
            "acc/test/DTD": 0.6228723526000977,
            "normalized_acc/test/DTD": 0.7516046166419983
        }
    ],
    "avg": [
        {
            "acc/test/avg": 0.7755572497844696,
            "normalized_acc/test/avg": 0.8518839478492737
        }
    ]
}