{
    "RESISC45": [
        {
            "acc/test/RESISC45_epoch": 0.9615873098373413,
            "loss/test/RESISC45_epoch": 0.13604702055454254,
            "acc/test/RESISC45": 0.9615873098373413,
            "normalized_acc/test/RESISC45": 0.9947454929351807
        }
    ],
    "Flowers102": [
        {
            "acc/test/Flowers102_epoch": 0.8970564603805542,
            "loss/test/Flowers102_epoch": 0.41023707389831543,
            "acc/test/Flowers102": 0.8970564603805542,
            "normalized_acc/test/Flowers102": 0.9520193338394165
        }
    ],
    "avg": [
        {
            "acc/test/avg": 0.9293218851089478,
            "normalized_acc/test/avg": 0.9733824133872986
        }
    ]
}