{
    "RESISC45": [
        {
            "acc/test/RESISC45_epoch": 0.8014285564422607,
            "loss/test/RESISC45_epoch": 0.6233789920806885,
            "acc/test/RESISC45": 0.8014285564422607,
            "normalized_acc/test/RESISC45": 0.8290640711784363
        }
    ],
    "FER2013": [
        {
            "acc/test/FER2013_epoch": 0.6217609643936157,
            "loss/test/FER2013_epoch": 1.0668364763259888,
            "acc/test/FER2013": 0.6217609643936157,
            "normalized_acc/test/FER2013": 0.843348503112793
        }
    ],
    "avg": [
        {
            "acc/test/avg": 0.7115947604179382,
            "normalized_acc/test/avg": 0.8362062871456146
        }
    ]
}