{
    "GTSRB": [
        {
            "acc/test/GTSRB_epoch": 0.9068092107772827,
            "loss/test/GTSRB_epoch": 0.4214092195034027,
            "acc/test/GTSRB": 0.9068092107772827,
            "normalized_acc/test/GTSRB": 0.9167534112930298
        }
    ],
    "DTD": [
        {
            "acc/test/DTD_epoch": 0.6265957355499268,
            "loss/test/DTD_epoch": 1.2998634576797485,
            "acc/test/DTD": 0.6265957355499268,
            "normalized_acc/test/DTD": 0.7560975551605225
        }
    ],
    "avg": [
        {
            "acc/test/avg": 0.7667024731636047,
            "normalized_acc/test/avg": 0.8364254832267761
        }
    ]
}