{
    "Flowers102": [
        {
            "acc/test/Flowers102_epoch": 0.9144576191902161,
            "loss/test/Flowers102_epoch": 0.34238412976264954,
            "acc/test/Flowers102": 0.9144576191902161,
            "normalized_acc/test/Flowers102": 0.9704866409301758
        }
    ],
    "FER2013": [
        {
            "acc/test/FER2013_epoch": 0.7472833395004272,
            "loss/test/FER2013_epoch": 1.1452271938323975,
            "acc/test/FER2013": 0.7472833395004272,
            "normalized_acc/test/FER2013": 1.0136053562164307
        }
    ],
    "avg": [
        {
            "acc/test/avg": 0.8308704793453217,
            "normalized_acc/test/avg": 0.9920459985733032
        }
    ]
}