{
    "DTD": [
        {
            "acc/test/DTD_epoch": 0.6441489458084106,
            "loss/test/DTD_epoch": 1.2614524364471436,
            "acc/test/DTD": 0.6441489458084106,
            "normalized_acc/test/DTD": 0.7772785425186157
        }
    ],
    "Flowers102": [
        {
            "acc/test/Flowers102_epoch": 0.816067636013031,
            "loss/test/Flowers102_epoch": 0.768773078918457,
            "acc/test/Flowers102": 0.816067636013031,
            "normalized_acc/test/Flowers102": 0.8660683035850525
        }
    ],
    "avg": [
        {
            "acc/test/avg": 0.7301082909107208,
            "normalized_acc/test/avg": 0.8216734230518341
        }
    ]
}