{
    "DTD": [
        {
            "acc/test/DTD_epoch": 0.5244680643081665,
            "loss/test/DTD_epoch": 1.7296913862228394,
            "acc/test/DTD": 0.5244680643081665,
            "normalized_acc/test/DTD": 0.6707482933998108
        }
    ],
    "FashionMNIST": [
        {
            "acc/test/FashionMNIST_epoch": 0.8037999868392944,
            "loss/test/FashionMNIST_epoch": 0.586902379989624,
            "acc/test/FashionMNIST": 0.8037999868392944,
            "normalized_acc/test/FashionMNIST": 0.8536533117294312
        }
    ],
    "avg": [
        {
            "acc/test/avg": 0.6641340255737305,
            "normalized_acc/test/avg": 0.762200802564621
        }
    ]
}