{
    "DTD": [
        {
            "acc/test/DTD_epoch": 0.792553186416626,
            "loss/test/DTD_epoch": 0.8771637082099915,
            "acc/test/DTD": 0.792553186416626,
            "normalized_acc/test/DTD": 0.9563542604446411
        }
    ],
    "FER2013": [
        {
            "acc/test/FER2013_epoch": 0.7411535382270813,
            "loss/test/FER2013_epoch": 1.1378111839294434,
            "acc/test/FER2013": 0.7411535382270813,
            "normalized_acc/test/FER2013": 1.0052909851074219
        }
    ],
    "avg": [
        {
            "acc/test/avg": 0.7668533623218536,
            "normalized_acc/test/avg": 0.9808226227760315
        }
    ]
}