{
    "Flowers102": [
        {
            "acc/test/Flowers102_epoch": 0.856399416923523,
            "loss/test/Flowers102_epoch": 0.5305705666542053,
            "acc/test/Flowers102": 0.856399416923523,
            "normalized_acc/test/Flowers102": 0.9088712334632874
        }
    ],
    "FashionMNIST": [
        {
            "acc/test/FashionMNIST_epoch": 0.9490000009536743,
            "loss/test/FashionMNIST_epoch": 0.1717279553413391,
            "acc/test/FashionMNIST": 0.9490000009536743,
            "normalized_acc/test/FashionMNIST": 0.9968487024307251
        }
    ],
    "avg": [
        {
            "acc/test/avg": 0.9026997089385986,
            "normalized_acc/test/avg": 0.9528599679470062
        }
    ]
}